airflow/providers/huawei/__init__.py
airflow/providers/huawei/get_provider_info.py
airflow/providers/huawei/cloud/__init__.py
airflow/providers/huawei/cloud/hooks/__init__.py
airflow/providers/huawei/cloud/hooks/base_huawei_cloud.py
airflow/providers/huawei/cloud/hooks/cdm.py
airflow/providers/huawei/cloud/hooks/dataarts.py
airflow/providers/huawei/cloud/hooks/dli.py
airflow/providers/huawei/cloud/hooks/dws.py
airflow/providers/huawei/cloud/hooks/dws_sql.py
airflow/providers/huawei/cloud/hooks/huawei_obs.py
airflow/providers/huawei/cloud/hooks/modelarts.py
airflow/providers/huawei/cloud/hooks/mrs.py
airflow/providers/huawei/cloud/hooks/smn.py
airflow/providers/huawei/cloud/operators/__init__.py
airflow/providers/huawei/cloud/operators/cdm.py
airflow/providers/huawei/cloud/operators/dataarts.py
airflow/providers/huawei/cloud/operators/dli.py
airflow/providers/huawei/cloud/operators/dws.py
airflow/providers/huawei/cloud/operators/huawei_obs.py
airflow/providers/huawei/cloud/operators/modelarts.py
airflow/providers/huawei/cloud/operators/mrs.py
airflow/providers/huawei/cloud/operators/smn.py
airflow/providers/huawei/cloud/sensors/__init__.py
airflow/providers/huawei/cloud/sensors/cdm.py
airflow/providers/huawei/cloud/sensors/dataarts.py
airflow/providers/huawei/cloud/sensors/dli.py
airflow/providers/huawei/cloud/sensors/dws.py
airflow/providers/huawei/cloud/sensors/huawei_obs_key.py
airflow/providers/huawei/cloud/sensors/modelarts.py
airflow/providers/huawei/cloud/sensors/mrs.py
airflow/providers/huawei/cloud/triggers/__init__.py
airflow/providers/huawei/cloud/triggers/dli.py
airflow/providers/huawei/cloud/triggers/mrs.py
airflow/providers/huawei/cloud/utils/__init__.py
airflow/providers/huawei/cloud/utils/signer.py
apache_airflow_providers_huawei-1.7.0.dist-info/LICENSE
apache_airflow_providers_huawei-1.7.0.dist-info/METADATA
apache_airflow_providers_huawei-1.7.0.dist-info/NOTICE
apache_airflow_providers_huawei-1.7.0.dist-info/WHEEL
apache_airflow_providers_huawei-1.7.0.dist-info/entry_points.txt
apache_airflow_providers_huawei-1.7.0.dist-info/top_level.txt
apache_airflow_providers_huawei-1.7.0.dist-info/RECORD
