Metadata-Version: 2.1
Name: apache-airflow-providers-huawei
Version: 1.7.0
Summary: Provider for Apache Airflow. Implements apache-airflow-providers-huawei package
Home-page: https://airflow.apache.org/
Download-URL: https://archive.apache.org/dist/airflow/providers
Author: Apache Software Foundation
Author-email: dev@airflow.apache.org
License: Apache License 2.0
Project-URL: Documentation, https://airflow.apache.org/docs/apache-airflow-providers-huawei/1.7.0/
Project-URL: Bug Tracker, https://github.com/apache/airflow/issues
Project-URL: Source Code, https://github.com/apache/airflow
Project-URL: Slack Chat, https://s.apache.org/airflow-slack
Project-URL: Twitter, https://twitter.com/ApacheAirflow
Project-URL: YouTube, https://www.youtube.com/channel/UCSXwxpWZQ7XZ1WL3wqevChA/
Classifier: Development Status :: 5 - Production/Stable
Classifier: Environment :: Console
Classifier: Environment :: Web Environment
Classifier: Intended Audience :: Developers
Classifier: Intended Audience :: System Administrators
Classifier: Framework :: Apache Airflow
Classifier: Framework :: Apache Airflow :: Provider
Classifier: License :: OSI Approved :: Apache Software License
Classifier: Programming Language :: Python :: 3.7
Classifier: Programming Language :: Python :: 3.8
Classifier: Programming Language :: Python :: 3.9
Classifier: Programming Language :: Python :: 3.10
Classifier: Topic :: System :: Monitoring
Requires-Python: ~=3.7
License-File: LICENSE
License-File: NOTICE
Requires-Dist: apache-airflow >=2.5.0
Requires-Dist: esdk-obs-python >=3.22.2
Requires-Dist: huaweicloudsdkcdm >=3.1.78
Requires-Dist: huaweicloudsdkcore >=3.1.78
Requires-Dist: huaweicloudsdkdlf >=3.1.19
Requires-Dist: huaweicloudsdkdli ==3.1.67
Requires-Dist: huaweicloudsdkdws >=3.1.21
Requires-Dist: huaweicloudsdkiam >=3.1.19
Requires-Dist: huaweicloudsdkmrs >=3.1.58
Requires-Dist: huaweicloudsdksmn >=3.1.19
Requires-Dist: psycopg2 >=2.9.4
Provides-Extra: common.sql
Requires-Dist: apache-airflow-providers-common-sql ; extra == 'common.sql'
